[
  {
    "id": "quest_pressure-0",
    "name": "小",
    "weightPermil": 1
  },
  {
    "id": "quest_pressure-1",
    "name": "小",
    "weightPermil": 143
  },
  {
    "id": "quest_pressure-2",
    "name": "普通",
    "weightPermil": 999
  },
  {
    "id": "quest_pressure-3",
    "name": "中",
    "weightPermil": 1571
  },
  {
    "id": "quest_pressure-4",
    "name": "大",
    "weightPermil": 1857
  },
  {
    "id": "quest_pressure-5",
    "name": "特大",
    "weightPermil": 2500
  }
]